README.md
setup.py
rasa_addons/__init__.py
rasa_addons/utils.py
rasa_addons.egg-info/PKG-INFO
rasa_addons.egg-info/SOURCES.txt
rasa_addons.egg-info/dependency_links.txt
rasa_addons.egg-info/requires.txt
rasa_addons.egg-info/top_level.txt
rasa_addons/core/__init__.py
rasa_addons/core/actions/__init__.py
rasa_addons/core/actions/action_botfront_disambiguation.py
rasa_addons/core/actions/action_botfront_mapping.py
rasa_addons/core/channels/__init__.py
rasa_addons/core/channels/facebook_messenger.py
rasa_addons/core/channels/graphql.py
rasa_addons/core/channels/rest.py
rasa_addons/core/channels/rest_plus.py
rasa_addons/core/channels/webchat.py
rasa_addons/core/channels/webchat_plus.py
rasa_addons/core/nlg/__init__.py
rasa_addons/core/nlg/bftemplate.py
rasa_addons/core/nlg/graphql.py
rasa_addons/core/policies/__init__.py
rasa_addons/core/policies/disambiguation.py
rasa_addons/core/policies/mapping.py
rasa_addons/core/tracker_stores/__init__.py
rasa_addons/core/tracker_stores/botfront.py
rasa_addons/importers/__init__.py
rasa_addons/importers/botfront.py
rasa_addons/nlu/__init__.py
rasa_addons/nlu/components/__init__.py
rasa_addons/nlu/components/duckling_crf_merger.py
rasa_addons/nlu/components/duckling_http_extractor.py
rasa_addons/nlu/components/entities_filter.py
rasa_addons/nlu/components/entity_synonyms_endpoints.py
rasa_addons/nlu/components/gazette.py
rasa_addons/nlu/components/intent_ranking_canonical_example_injector.py
rasa_addons/nlu/components/sweeper.py