Metadata-Version: 2.1
Name: rasa-addons
Version: 0.9.24
Summary: Rasa Addons - Components for Rasa and Botfront
Home-page: https://botfront.io
Author: Botfront
Author-email: hi@botfront.io
License: Apache 2.0
Platform: UNKNOWN
